MANIFEST.in
README.md
setup.py
pypremailer/__init__.py
pypremailer/core.py
python_premailer.egg-info/PKG-INFO
python_premailer.egg-info/SOURCES.txt
python_premailer.egg-info/dependency_links.txt
python_premailer.egg-info/requires.txt
python_premailer.egg-info/top_level.txt