Metadata-Version: 1.0
Name: python-premailer
Version: 0.5.7
Summary: Prepare HTML for email; embedd CSS to inline.
Home-page: http://github.com/ralphbean/python-premailer
Author: Ralph Bean
Author-email: ralph.bean@gmail.com
License: UNKNOWN
Platform: UNKNOWN
